exemplotestbench/fulladder.v
module fulladder(
    input a,
    input b,
    input cin,
    output cout,
    output s
);

wire xor_ab;
wire and_ab, and_ac, and_bc;

xor (xor_ab, a, b);
xor (s , xor_ab, cin);

and (and_ab, a, b);
and (and_bc, b, cin);
and (and_ac, a, cin);

or (cout, and_ab, and_ac, and_bc);

endmodule

exemplotestbench/adder4bits.v
module adder4bits(
    input [3:0] a,
    input [3:0] b,
    output [4:0] s
);

    wire [2:0] cout;

    fulladder fa1( .a(a[0]), .b(b[0]), .cout(cout[0]), .cin(1'b0), .s(s[0]));
    fulladder fa2( .a(a[1]), .b(b[1]), .cout(cout[1]), .cin(cout[0]), .s(s[1]));
    fulladder fa3( .a(a[2]), .b(b[2]), .cout(cout[2]), .cin(cout[1]), .s(s[2]));
    fulladder fa4( .a(a[3]), .b(b[3]), .cout(s[4]), .cin(cout[2]), .s(s[3]));
endmodule

exemplotestbench/adder4bits_tb.v
`timescale 1ns/1ns



module adder4bits_tb;
    // Declarações para os sinais de teste
    reg [3:0] a, b;
    wire [4:0] s;

    // Instanciação do DUT
    adder4bits DUT (
        .a(a),
        .b(b),
        .s(s)
    );

    // Bloco para inicializar o dump de formas de onda.
    initial begin
        $dumpfile("adder4bits_tb.vcd"); // Nome do arquivo de saída
        $dumpvars(0, adder4bits_tb);    // Registrar todas as variáveis deste módulo
    end

    /*****************
    *   DRIVER       *
    ******************/
    // Bloco always para gerar estímulos (driver)
    // lembrando: bloco initial executa uma só vez no inicio da simulação
    // e nao é sintetizável.
    initial begin
        // Gera todas as combinações possíveis de 'a' e 'b'
        /*
        for (a = 0; a < 16; a = a + 1) begin
            $display("Gerando estimulos: valores de b para a = %b", a);
            for (b = 0; b < 16; b = b + 1) begin
                #10; // Esperar 10 unidades de tempo
            end
        end
        */
        ///// PARA TESTAR COM FOR, COMENTE DAQUI
        a= 4'b0000;
        repeat (16) begin
            $display("Gerando estimulos: valores de b para a = %b", a);
            repeat (16) begin
                #10; // Esperar 10 unidades de tempo
                b = b + 1;
            end
            b = 4'b0000; // Resetar b
            a = a + 1;
        end
        ///// ATE AQUI
        // Finaliza a simulação
        #10;
        $finish;
    end

    /*****************
    *   MONITOR      *
    ******************/
    // Variável para armazenar o resultado esperado.
    reg [4:0] expected_sum;
    // Bloco always para calcular a soma esperada e monitorar a saída
    // será disparado sempre que detecta mudança nas variáveis na lista de sensibilidade
    always @(a, b) begin
        expected_sum = a + b; // modelo de referencia. Calcula o resultado correto.
        #1; // Aguardar tempo suficiente para o DUT processar os sinais
        if (s === expected_sum) begin
            //$display("OKAY: a = %b e b = %b", a, b); // habilite e veja ficar lento. :)
            // Na real, interessa imprimir apenas se der erro. Se tá certinho, segue o baile.
        end else begin
            $display("ERRO: a = %b e b = %b: esperado = %b, obtido = %b", a, b, expected_sum, s);
        end
    end
endmodule

exemplotestbench/adder4bits_tb.vcd
$date
	Tue Oct 21 00:02:01 2025
$end
$version
	Icarus Verilog
$end
$timescale
	1ns
$end
$scope module adder4bits_tb $end
$var wire 5 ! s [4:0] $end
$var reg 4 " a [3:0] $end
$var reg 4 # b [3:0] $end
$var reg 5 $ expected_sum [4:0] $end
$scope module DUT $end
$var wire 4 % a [3:0] $end
$var wire 4 & b [3:0] $end
$var wire 5 ' s [4:0] $end
$var wire 3 ( cout [2:0] $end
$scope module fa1 $end
$var wire 1 ) a $end
$var wire 1 * and_ab $end
$var wire 1 + and_ac $end
$var wire 1 , and_bc $end
$var wire 1 - b $end
$var wire 1 . cin $end
$var wire 1 / cout $end
$var wire 1 0 s $end
$var wire 1 1 xor_ab $end
$upscope $end
$scope module fa2 $end
$var wire 1 2 a $end
$var wire 1 3 and_ab $end
$var wire 1 4 and_ac $end
$var wire 1 5 and_bc $end
$var wire 1 6 b $end
$var wire 1 7 cin $end
$var wire 1 8 cout $end
$var wire 1 9 s $end
$var wire 1 : xor_ab $end
$upscope $end
$scope module fa3 $end
$var wire 1 ; a $end
$var wire 1 < and_ab $end
$var wire 1 = and_ac $end
$var wire 1 > and_bc $end
$var wire 1 ? b $end
$var wire 1 @ cin $end
$var wire 1 A cout $end
$var wire 1 B s $end
$var wire 1 C xor_ab $end
$upscope $end
$scope module fa4 $end
$var wire 1 D a $end
$var wire 1 E and_ab $end
$var wire 1 F and_ac $end
$var wire 1 G and_bc $end
$var wire 1 H b $end
$var wire 1 I cin $end
$var wire 1 J cout $end
$var wire 1 K s $end
$var wire 1 L xor_ab $end
$upscope $end
$upscope $end
$upscope $end
$enddefinitions $end
$comment Show the parameter values. $end
$dumpall
$end
#0
$dumpvars
xL
xK
0J
0I
xH
0G
0F
0E
0D
xC
xB
0A
0@
x?
0>
0=
0<
0;
x:
x9
08
07
x6
05
04
03
02
x1
x0
0/
0.
x-
0,
0+
0*
0)
b0 (
b0xxxx '
bx &
b0 %
bx $
bx #
b0 "
b0xxxx !
$end
#160
10
09
0B
b1 !
b1 '
0K
11
0:
0C
0L
1)
0-
06
0?
0H
b1 $
b1 "
b1 %
b0 #
b0 &
#170
19
17
b10 !
b10 '
00
b1 (
1/
01
1*
1-
b10 $
b1 #
b1 &
#180
0B
07
0@
10
0/
b11 !
b11 '
19
b0 (
08
11
0*
1:
05
0-
16
b11 $
b10 #
b10 &
#190
1B
1@
18
09
15
17
b100 !
b100 '
00
b11 (
1/
01
1*
1-
b100 $
b11 #
b11 &
#200
0K
07
0@
0I
10
0/
09
08
b101 !
b101 '
1B
b0 (
0A
11
0*
0:
05
1C
0>
0-
06
1?
b101 $
b100 #
b100 &
#210
19
17
b110 !
b110 '
00
b1 (
1/
01
1*
1-
b110 $
b101 #
b101 &
#220
0K
0I
0A
1B
0>
07
0@
10
0/
b111 !
b111 '
19
b0 (
08
11
0*
1:
05
0-
16
b111 $
b110 #
b110 &
#230
1K
1I
1A
0B
1>
1@
18
09
15
17
b1000 !
b1000 '
00
b111 (
1/
01
1*
1-
b1000 $
b111 #
b111 &
#240
07
0@
0I
10
0/
09
08
0B
b0 (
0A
1K
b1001 !
b1001 '
0J
11
0*
0:
05
0C
0>
1L
0G
0-
06
0?
1H
b1001 $
b1000 #
b1000 &
#250
19
17
b1010 !
b1010 '
00
b1 (
1/
01
1*
1-
b1010 $
b1001 #
b1001 &
#260
0B
07
0@
10
0/
b1011 !
b1011 '
19
b0 (
08
11
0*
1:
05
0-
16
b1011 $
b1010 #
b1010 &
#270
1B
1@
18
09
15
17
b1100 !
b1100 '
00
b11 (
1/
01
1*
1-
b1100 $
b1011 #
b1011 &
#280
0J
1K
0G
07
0@
0I
10
0/
09
08
b1101 !
b1101 '
1B
b0 (
0A
11
0*
0:
05
1C
0>
0-
06
1?
b1101 $
b1100 #
b1100 &
#290
19
17
b1110 !
b1110 '
00
b1 (
1/
01
1*
1-
b1110 $
b1101 #
b1101 &
#300
0J
1K
0G
0I
0A
1B
0>
07
0@
10
0/
b1111 !
b1111 '
19
b0 (
08
11
0*
1:
05
0-
16
b1111 $
b1110 #
b1110 &
#310
1J
0K
1G
1I
1A
0B
1>
1@
18
09
15
17
b10000 !
b10000 '
00
b111 (
1/
01
1*
1-
b10000 $
b1111 #
b1111 &
#320
0@
08
19
07
0I
0/
0B
b0 (
0A
0K
b10 !
b10 '
0J
04
0*
05
0C
0>
0L
0G
0)
12
0-
06
0?
0H
b10 $
b10 "
b10 %
b0 #
b0 &
#330
b11 !
b11 '
10
11
1-
b11 $
b1 #
b1 &
#340
1B
1@
00
b100 !
b100 '
09
b10 (
18
01
0:
13
0-
16
b100 $
b10 #
b10 &
#350
b101 !
b101 '
10
11
1-
b101 $
b11 #
b11 &
#360
0K
0@
0I
00
19
08
b110 !
b110 '
1B
b0 (
0A
01
1:
03
1C
0>
0-
06
1?
b110 $
b100 #
b100 &
#370
b111 !
b111 '
10
11
1-
b111 $
b101 #
b101 &
#380
1K
1I
1A
0B
1>
1@
00
b1000 !
b1000 '
09
b110 (
18
01
0:
13
0-
16
b1000 $
b110 #
b110 &
#390
b1001 !
b1001 '
10
11
1-
b1001 $
b111 #
b111 &
#400
0@
0I
00
19
08
0B
b0 (
0A
1K
b1010 !
b1010 '
0J
01
1:
03
0C
0>
1L
0G
0-
06
0?
1H
b1010 $
b1000 #
b1000 &
#410
b1011 !
b1011 '
10
11
1-
b1011 $
b1001 #
b1001 &
#420
1B
1@
00
b1100 !
b1100 '
09
b10 (
18
01
0:
13
0-
16
b1100 $
b1010 #
b1010 &
#430
b1101 !
b1101 '
10
11
1-
b1101 $
b1011 #
b1011 &
#440
0J
1K
0G
0@
0I
00
19
08
b1110 !
b1110 '
1B
b0 (
0A
01
1:
03
1C
0>
0-
06
1?
b1110 $
b1100 #
b1100 &
#450
b1111 !
b1111 '
10
11
1-
b1111 $
b1101 #
b1101 &
#460
1J
0K
1G
1I
1A
0B
1>
1@
00
b10000 !
b10000 '
09
b110 (
18
01
0:
13
0-
16
b10000 $
b1110 #
b1110 &
#470
b10001 !
b10001 '
10
11
1-
b10001 $
b1111 #
b1111 &
#480
0@
0I
19
08
0B
b0 (
0A
0K
b11 !
b11 '
0J
1:
03
0C
0>
0L
0G
1)
0-
06
0?
0H
b11 $
b11 "
b11 %
b0 #
b0 &
#490
1B
1@
18
09
14
17
b100 !
b100 '
00
b11 (
1/
01
1*
1-
b100 $
b1 #
b1 &
#500
04
07
10
b10 (
0/
b101 !
b101 '
09
11
0*
0:
13
05
0-
16
b101 $
b10 #
b10 &
#510
19
15
14
17
b110 !
b110 '
00
b11 (
1/
01
1*
1-
b110 $
b11 #
b11 &
#520
0@
08
04
0K
07
0I
10
0/
19
b111 !
b111 '
1B
b0 (
0A
11
0*
1:
03
05
1C
0>
0-
06
1?
b111 $
b100 #
b100 &
#530
1K
1I
1A
0B
1>
1@
18
09
14
17
b1000 !
b1000 '
00
b111 (
1/
01
1*
1-
b1000 $
b101 #
b101 &
#540
04
07
10
b110 (
0/
b1001 !
b1001 '
09
11
0*
0:
13
05
0-
16
b1001 $
b110 #
b110 &
#550
19
15
14
17
b1010 !
b1010 '
00
b111 (
1/
01
1*
1-
b1010 $
b111 #
b111 &
#560
0@
08
04
07
0I
10
0/
19
0B
b0 (
0A
1K
b1011 !
b1011 '
0J
11
0*
1:
03
05
0C
0>
1L
0G
0-
06
0?
1H
b1011 $
b1000 #
b1000 &
#570
1B
1@
18
09
14
17
b1100 !
b1100 '
00
b11 (
1/
01
1*
1-
b1100 $
b1001 #
b1001 &
#580
04
07
10
b10 (
0/
b1101 !
b1101 '
09
11
0*
0:
13
05
0-
16
b1101 $
b1010 #
b1010 &
#590
19
15
14
17
b1110 !
b1110 '
00
b11 (
1/
01
1*
1-
b1110 $
b1011 #
b1011 &
#600
0@
08
0J
04
1K
0G
07
0I
10
0/
19
b1111 !
b1111 '
1B
b0 (
0A
11
0*
1:
03
05
1C
0>
0-
06
1?
b1111 $
b1100 #
b1100 &
#610
1J
0K
1G
1I
1A
0B
1>
1@
18
09
14
17
b10000 !
b10000 '
00
b111 (
1/
01
1*
1-
b10000 $
b1101 #
b1101 &
#620
04
07
10
b110 (
0/
b10001 !
b10001 '
09
11
0*
0:
13
05
0-
16
b10001 $
b1110 #
b1110 &
#630
19
15
14
17
b10010 !
b10010 '
00
b111 (
1/
01
1*
1-
b10010 $
b1111 #
b1111 &
#640
0I
0A
09
1B
07
0@
0/
b0 (
08
0K
b100 !
b100 '
0J
04
0=
0*
03
05
0>
0L
0G
0)
02
1;
0-
06
0?
0H
b100 $
b100 "
b100 %
b0 #
b0 &
#650
b101 !
b101 '
10
11
1-
b101 $
b1 #
b1 &
#660
00
b110 !
b110 '
19
01
1:
0-
16
b110 $
b10 #
b10 &
#670
b111 !
b111 '
10
11
1-
b111 $
b11 #
b11 &
#680
1K
1I
00
09
b1000 !
b1000 '
0B
b100 (
1A
01
0:
0C
1<
0-
06
1?
b1000 $
b100 #
b100 &
#690
b1001 !
b1001 '
10
11
1-
b1001 $
b101 #
b101 &
#700
00
b1010 !
b1010 '
19
01
1:
0-
16
b1010 $
b110 #
b110 &
#710
b1011 !
b1011 '
10
11
1-
b1011 $
b111 #
b111 &
#720
0I
00
09
1B
b0 (
0A
1K
b1100 !
b1100 '
0J
01
0:
1C
0<
1L
0G
0-
06
0?
1H
b1100 $
b1000 #
b1000 &
#730
b1101 !
b1101 '
10
11
1-
b1101 $
b1001 #
b1001 &
#740
00
b1110 !
b1110 '
19
01
1:
0-
16
b1110 $
b1010 #
b1010 &
#750
b1111 !
b1111 '
10
11
1-
b1111 $
b1011 #
b1011 &
#760
1J
0K
1G
1I
00
09
b10000 !
b10000 '
0B
b100 (
1A
01
0:
0C
1<
0-
06
1?
b10000 $
b1100 #
b1100 &
#770
b10001 !
b10001 '
10
11
1-
b10001 $
b1101 #
b1101 &
#780
00
b10010 !
b10010 '
19
01
1:
0-
16
b10010 $
b1110 #
b1110 &
#790
b10011 !
b10011 '
10
11
1-
b10011 $
b1111 #
b1111 &
#800
0I
09
1B
b0 (
0A
0K
b101 !
b101 '
0J
0:
1C
0<
0L
0G
1)
0-
06
0?
0H
b101 $
b101 "
b101 %
b0 #
b0 &
#810
19
17
b110 !
b110 '
00
b1 (
1/
01
1*
1-
b110 $
b1 #
b1 &
#820
0K
0I
0A
1B
0=
07
0@
10
0/
b111 !
b111 '
19
b0 (
08
11
0*
1:
05
0-
16
b111 $
b10 #
b10 &
#830
1K
1I
1A
0B
1=
1@
18
09
15
17
b1000 !
b1000 '
00
b111 (
1/
01
1*
1-
b1000 $
b11 #
b11 &
#840
0=
07
0@
10
0/
09
b100 (
08
b1001 !
b1001 '
0B
11
0*
0:
05
0C
1<
0>
0-
06
1?
b1001 $
b100 #
b100 &
#850
19
17
b1010 !
b1010 '
00
b101 (
1/
01
1*
1-
b1010 $
b101 #
b101 &
#860
0B
0>
0=
07
0@
10
0/
b1011 !
b1011 '
19
b100 (
08
11
0*
1:
05
0-
16
b1011 $
b110 #
b110 &
#870
1B
1>
1=
1@
18
09
15
17
b1100 !
b1100 '
00
b111 (
1/
01
1*
1-
b1100 $
b111 #
b111 &
#880
0I
0A
0=
07
0@
10
0/
09
b0 (
08
1B
1K
b1101 !
b1101 '
0J
11
0*
0:
05
1C
0<
0>
1L
0G
0-
06
0?
1H
b1101 $
b1000 #
b1000 &
#890
19
17
b1110 !
b1110 '
00
b1 (
1/
01
1*
1-
b1110 $
b1001 #
b1001 &
#900
0J
1K
0G
0I
0A
1B
0=
07
0@
10
0/
b1111 !
b1111 '
19
b0 (
08
11
0*
1:
05
0-
16
b1111 $
b1010 #
b1010 &
#910
1J
0K
1G
1I
1A
0B
1=
1@
18
09
15
17
b10000 !
b10000 '
00
b111 (
1/
01
1*
1-
b10000 $
b1011 #
b1011 &
#920
0=
07
0@
10
0/
09
b100 (
08
b10001 !
b10001 '
0B
11
0*
0:
05
0C
1<
0>
0-
06
1?
b10001 $
b1100 #
b1100 &
#930
19
17
b10010 !
b10010 '
00
b101 (
1/
01
1*
1-
b10010 $
b1101 #
b1101 &
#940
0B
0>
0=
07
0@
10
0/
b10011 !
b10011 '
19
b100 (
08
11
0*
1:
05
0-
16
b10011 $
b1110 #
b1110 &
#950
1B
1>
1=
1@
18
09
15
17
b10100 !
b10100 '
00
b111 (
1/
01
1*
1-
b10100 $
b1111 #
b1111 &
#960
0I
0A
0=
0@
08
19
07
b0 (
0/
1B
0K
b110 !
b110 '
0J
04
0*
05
1C
0<
0>
0L
0G
0)
12
0-
06
0?
0H
b110 $
b110 "
b110 %
b0 #
b0 &
#970
b111 !
b111 '
10
11
1-
b111 $
b1 #
b1 &
#980
1K
1I
1A
0B
1=
1@
00
b1000 !
b1000 '
09
b110 (
18
01
0:
13
0-
16
b1000 $
b10 #
b10 &
#990
b1001 !
b1001 '
10
11
1-
b1001 $
b11 #
b11 &
#1000
0=
0@
00
19
b100 (
08
b1010 !
b1010 '
0B
01
1:
03
0C
1<
0>
0-
06
1?
b1010 $
b100 #
b100 &
#1010
b1011 !
b1011 '
10
11
1-
b1011 $
b101 #
b101 &
#1020
1B
1>
1=
1@
00
b1100 !
b1100 '
09
b110 (
18
01
0:
13
0-
16
b1100 $
b110 #
b110 &
#1030
b1101 !
b1101 '
10
11
1-
b1101 $
b111 #
b111 &
#1040
0I
0A
0=
0@
00
19
b0 (
08
1B
1K
b1110 !
b1110 '
0J
01
1:
03
1C
0<
0>
1L
0G
0-
06
0?
1H
b1110 $
b1000 #
b1000 &
#1050
b1111 !
b1111 '
10
11
1-
b1111 $
b1001 #
b1001 &
#1060
1J
0K
1G
1I
1A
0B
1=
1@
00
b10000 !
b10000 '
09
b110 (
18
01
0:
13
0-
16
b10000 $
b1010 #
b1010 &
#1070
b10001 !
b10001 '
10
11
1-
b10001 $
b1011 #
b1011 &
#1080
0=
0@
00
19
b100 (
08
b10010 !
b10010 '
0B
01
1:
03
0C
1<
0>
0-
06
1?
b10010 $
b1100 #
b1100 &
#1090
b10011 !
b10011 '
10
11
1-
b10011 $
b1101 #
b1101 &
#1100
1B
1>
1=
1@
00
b10100 !
b10100 '
09
b110 (
18
01
0:
13
0-
16
b10100 $
b1110 #
b1110 &
#1110
b10101 !
b10101 '
10
11
1-
b10101 $
b1111 #
b1111 &
#1120
0I
0A
0=
0@
19
b0 (
08
1B
0K
b111 !
b111 '
0J
1:
03
1C
0<
0>
0L
0G
1)
0-
06
0?
0H
b111 $
b111 "
b111 %
b0 #
b0 &
#1130
1K
1I
1A
0B
1=
1@
18
09
14
17
b1000 !
b1000 '
00
b111 (
1/
01
1*
1-
b1000 $
b1 #
b1 &
#1140
04
07
10
b110 (
0/
b1001 !
b1001 '
09
11
0*
0:
13
05
0-
16
b1001 $
b10 #
b10 &
#1150
19
15
14
17
b1010 !
b1010 '
00
b111 (
1/
01
1*
1-
b1010 $
b11 #
b11 &
#1160
0=
0@
08
04
07
10
b100 (
0/
19
b1011 !
b1011 '
0B
11
0*
1:
03
05
0C
1<
0>
0-
06
1?
b1011 $
b100 #
b100 &
#1170
1B
1>
1=
1@
18
09
14
17
b1100 !
b1100 '
00
b111 (
1/
01
1*
1-
b1100 $
b101 #
b101 &
#1180
04
07
10
b110 (
0/
b1101 !
b1101 '
09
11
0*
0:
13
05
0-
16
b1101 $
b110 #
b110 &
#1190
19
15
14
17
b1110 !
b1110 '
00
b111 (
1/
01
1*
1-
b1110 $
b111 #
b111 &
#1200
0I
0A
0=
0@
08
04
07
10
b0 (
0/
19
1B
1K
b1111 !
b1111 '
0J
11
0*
1:
03
05
1C
0<
0>
1L
0G
0-
06
0?
1H
b1111 $
b1000 #
b1000 &
#1210
1J
0K
1G
1I
1A
0B
1=
1@
18
09
14
17
b10000 !
b10000 '
00
b111 (
1/
01
1*
1-
b10000 $
b1001 #
b1001 &
#1220
04
07
10
b110 (
0/
b10001 !
b10001 '
09
11
0*
0:
13
05
0-
16
b10001 $
b1010 #
b1010 &
#1230
19
15
14
17
b10010 !
b10010 '
00
b111 (
1/
01
1*
1-
b10010 $
b1011 #
b1011 &
#1240
0=
0@
08
04
07
10
b100 (
0/
19
b10011 !
b10011 '
0B
11
0*
1:
03
05
0C
1<
0>
0-
06
1?
b10011 $
b1100 #
b1100 &
#1250
1B
1>
1=
1@
18
09
14
17
b10100 !
b10100 '
00
b111 (
1/
01
1*
1-
b10100 $
b1101 #
b1101 &
#1260
04
07
10
b110 (
0/
b10101 !
b10101 '
09
11
0*
0:
13
05
0-
16
b10101 $
b1110 #
b1110 &
#1270
19
15
14
17
b10110 !
b10110 '
00
b111 (
1/
01
1*
1-
b10110 $
b1111 #
b1111 &
#1280
0J
09
0B
b1000 !
b1000 '
1K
07
0@
0I
0/
08
b0 (
0A
04
0=
0F
0*
03
05
0<
0>
0G
0)
02
0;
1D
0-
06
0?
0H
b1000 $
b1000 "
b1000 %
b0 #
b0 &
#1290
b1001 !
b1001 '
10
11
1-
b1001 $
b1 #
b1 &
#1300
00
b1010 !
b1010 '
19
01
1:
0-
16
b1010 $
b10 #
b10 &
#1310
b1011 !
b1011 '
10
11
1-
b1011 $
b11 #
b11 &
#1320
00
09
b1100 !
b1100 '
1B
01
0:
1C
0-
06
1?
b1100 $
b100 #
b100 &
#1330
b1101 !
b1101 '
10
11
1-
b1101 $
b101 #
b101 &
#1340
00
b1110 !
b1110 '
19
01
1:
0-
16
b1110 $
b110 #
b110 &
#1350
b1111 !
b1111 '
10
11
1-
b1111 $
b111 #
b111 &
#1360
00
09
0B
0K
b10000 !
b10000 '
1J
01
0:
0C
0L
1E
0-
06
0?
1H
b10000 $
b1000 #
b1000 &
#1370
b10001 !
b10001 '
10
11
1-
b10001 $
b1001 #
b1001 &
#1380
00
b10010 !
b10010 '
19
01
1:
0-
16
b10010 $
b1010 #
b1010 &
#1390
b10011 !
b10011 '
10
11
1-
b10011 $
b1011 #
b1011 &
#1400
00
09
b10100 !
b10100 '
1B
01
0:
1C
0-
06
1?
b10100 $
b1100 #
b1100 &
#1410
b10101 !
b10101 '
10
11
1-
b10101 $
b1101 #
b1101 &
#1420
00
b10110 !
b10110 '
19
01
1:
0-
16
b10110 $
b1110 #
b1110 &
#1430
b10111 !
b10111 '
10
11
1-
b10111 $
b1111 #
b1111 &
#1440
09
0B
1K
b1001 !
b1001 '
0J
0:
0C
1L
0E
1)
0-
06
0?
0H
b1001 $
b1001 "
b1001 %
b0 #
b0 &
#1450
19
17
b1010 !
b1010 '
00
b1 (
1/
01
1*
1-
b1010 $
b1 #
b1 &
#1460
0B
07
0@
10
0/
b1011 !
b1011 '
19
b0 (
08
11
0*
1:
05
0-
16
b1011 $
b10 #
b10 &
#1470
1B
1@
18
09
15
17
b1100 !
b1100 '
00
b11 (
1/
01
1*
1-
b1100 $
b11 #
b11 &
#1480
0J
1K
0F
07
0@
0I
10
0/
09
08
b1101 !
b1101 '
1B
b0 (
0A
11
0*
0:
05
1C
0>
0-
06
1?
b1101 $
b100 #
b100 &
#1490
19
17
b1110 !
b1110 '
00
b1 (
1/
01
1*
1-
b1110 $
b101 #
b101 &
#1500
0J
1K
0F
0I
0A
1B
0>
07
0@
10
0/
b1111 !
b1111 '
19
b0 (
08
11
0*
1:
05
0-
16
b1111 $
b110 #
b110 &
#1510
1J
0K
1F
1I
1A
0B
1>
1@
18
09
15
17
b10000 !
b10000 '
00
b111 (
1/
01
1*
1-
b10000 $
b111 #
b111 &
#1520
0F
07
0@
0I
10
0/
09
08
0B
b0 (
0A
b10001 !
b10001 '
0K
11
0*
0:
05
0C
0>
0L
1E
0G
0-
06
0?
1H
b10001 $
b1000 #
b1000 &
#1530
19
17
b10010 !
b10010 '
00
b1 (
1/
01
1*
1-
b10010 $
b1001 #
b1001 &
#1540
0B
07
0@
10
0/
b10011 !
b10011 '
19
b0 (
08
11
0*
1:
05
0-
16
b10011 $
b1010 #
b1010 &
#1550
1B
1@
18
09
15
17
b10100 !
b10100 '
00
b11 (
1/
01
1*
1-
b10100 $
b1011 #
b1011 &
#1560
0K
0G
0F
07
0@
0I
10
0/
09
08
b10101 !
b10101 '
1B
b0 (
0A
11
0*
0:
05
1C
0>
0-
06
1?
b10101 $
b1100 #
b1100 &
#1570
19
17
b10110 !
b10110 '
00
b1 (
1/
01
1*
1-
b10110 $
b1101 #
b1101 &
#1580
0K
0G
0F
0I
0A
1B
0>
07
0@
10
0/
b10111 !
b10111 '
19
b0 (
08
11
0*
1:
05
0-
16
b10111 $
b1110 #
b1110 &
#1590
1K
1G
1F
1I
1A
0B
1>
1@
18
09
15
17
b11000 !
b11000 '
00
b111 (
1/
01
1*
1-
b11000 $
b1111 #
b1111 &
#1600
0@
08
0J
19
0F
07
0I
0/
0B
b0 (
0A
b1010 !
b1010 '
1K
04
0*
05
0C
0>
1L
0E
0G
0)
12
0-
06
0?
0H
b1010 $
b1010 "
b1010 %
b0 #
b0 &
#1610
b1011 !
b1011 '
10
11
1-
b1011 $
b1 #
b1 &
#1620
1B
1@
00
b1100 !
b1100 '
09
b10 (
18
01
0:
13
0-
16
b1100 $
b10 #
b10 &
#1630
b1101 !
b1101 '
10
11
1-
b1101 $
b11 #
b11 &
#1640
0J
1K
0F
0@
0I
00
19
08
b1110 !
b1110 '
1B
b0 (
0A
01
1:
03
1C
0>
0-
06
1?
b1110 $
b100 #
b100 &
#1650
b1111 !
b1111 '
10
11
1-
b1111 $
b101 #
b101 &
#1660
1J
0K
1F
1I
1A
0B
1>
1@
00
b10000 !
b10000 '
09
b110 (
18
01
0:
13
0-
16
b10000 $
b110 #
b110 &
#1670
b10001 !
b10001 '
10
11
1-
b10001 $
b111 #
b111 &
#1680
0F
0@
0I
00
19
08
0B
b0 (
0A
b10010 !
b10010 '
0K
01
1:
03
0C
0>
0L
1E
0G
0-
06
0?
1H
b10010 $
b1000 #
b1000 &
#1690
b10011 !
b10011 '
10
11
1-
b10011 $
b1001 #
b1001 &
#1700
1B
1@
00
b10100 !
b10100 '
09
b10 (
18
01
0:
13
0-
16
b10100 $
b1010 #
b1010 &
#1710
b10101 !
b10101 '
10
11
1-
b10101 $
b1011 #
b1011 &
#1720
0K
0G
0F
0@
0I
00
19
08
b10110 !
b10110 '
1B
b0 (
0A
01
1:
03
1C
0>
0-
06
1?
b10110 $
b1100 #
b1100 &
#1730
b10111 !
b10111 '
10
11
1-
b10111 $
b1101 #
b1101 &
#1740
1K
1G
1F
1I
1A
0B
1>
1@
00
b11000 !
b11000 '
09
b110 (
18
01
0:
13
0-
16
b11000 $
b1110 #
b1110 &
#1750
b11001 !
b11001 '
10
11
1-
b11001 $
b1111 #
b1111 &
#1760
0J
0F
0@
0I
19
08
0B
b0 (
0A
b1011 !
b1011 '
1K
1:
03
0C
0>
1L
0E
0G
1)
0-
06
0?
0H
b1011 $
b1011 "
b1011 %
b0 #
b0 &
#1770
1B
1@
18
09
14
17
b1100 !
b1100 '
00
b11 (
1/
01
1*
1-
b1100 $
b1 #
b1 &
#1780
04
07
10
b10 (
0/
b1101 !
b1101 '
09
11
0*
0:
13
05
0-
16
b1101 $
b10 #
b10 &
#1790
19
15
14
17
b1110 !
b1110 '
00
b11 (
1/
01
1*
1-
b1110 $
b11 #
b11 &
#1800
0@
08
0J
04
1K
0F
07
0I
10
0/
19
b1111 !
b1111 '
1B
b0 (
0A
11
0*
1:
03
05
1C
0>
0-
06
1?
b1111 $
b100 #
b100 &
#1810
1J
0K
1F
1I
1A
0B
1>
1@
18
09
14
17
b10000 !
b10000 '
00
b111 (
1/
01
1*
1-
b10000 $
b101 #
b101 &
#1820
04
07
10
b110 (
0/
b10001 !
b10001 '
09
11
0*
0:
13
05
0-
16
b10001 $
b110 #
b110 &
#1830
19
15
14
17
b10010 !
b10010 '
00
b111 (
1/
01
1*
1-
b10010 $
b111 #
b111 &
#1840
0@
08
04
0F
07
0I
10
0/
19
0B
b0 (
0A
b10011 !
b10011 '
0K
11
0*
1:
03
05
0C
0>
0L
1E
0G
0-
06
0?
1H
b10011 $
b1000 #
b1000 &
#1850
1B
1@
18
09
14
17
b10100 !
b10100 '
00
b11 (
1/
01
1*
1-
b10100 $
b1001 #
b1001 &
#1860
04
07
10
b10 (
0/
b10101 !
b10101 '
09
11
0*
0:
13
05
0-
16
b10101 $
b1010 #
b1010 &
#1870
19
15
14
17
b10110 !
b10110 '
00
b11 (
1/
01
1*
1-
b10110 $
b1011 #
b1011 &
#1880
0@
08
04
0K
0G
0F
07
0I
10
0/
19
b10111 !
b10111 '
1B
b0 (
0A
11
0*
1:
03
05
1C
0>
0-
06
1?
b10111 $
b1100 #
b1100 &
#1890
1K
1G
1F
1I
1A
0B
1>
1@
18
09
14
17
b11000 !
b11000 '
00
b111 (
1/
01
1*
1-
b11000 $
b1101 #
b1101 &
#1900
04
07
10
b110 (
0/
b11001 !
b11001 '
09
11
0*
0:
13
05
0-
16
b11001 $
b1110 #
b1110 &
#1910
19
15
14
17
b11010 !
b11010 '
00
b111 (
1/
01
1*
1-
b11010 $
b1111 #
b1111 &
#1920
0J
0F
0I
0A
09
1B
07
0@
0/
b0 (
08
b1100 !
b1100 '
1K
04
0=
0*
03
05
0>
1L
0E
0G
0)
02
1;
0-
06
0?
0H
b1100 $
b1100 "
b1100 %
b0 #
b0 &
#1930
b1101 !
b1101 '
10
11
1-
b1101 $
b1 #
b1 &
#1940
00
b1110 !
b1110 '
19
01
1:
0-
16
b1110 $
b10 #
b10 &
#1950
b1111 !
b1111 '
10
11
1-
b1111 $
b11 #
b11 &
#1960
1J
0K
1F
1I
00
09
b10000 !
b10000 '
0B
b100 (
1A
01
0:
0C
1<
0-
06
1?
b10000 $
b100 #
b100 &
#1970
b10001 !
b10001 '
10
11
1-
b10001 $
b101 #
b101 &
#1980
00
b10010 !
b10010 '
19
01
1:
0-
16
b10010 $
b110 #
b110 &
#1990
b10011 !
b10011 '
10
11
1-
b10011 $
b111 #
b111 &
#2000
0F
0I
00
09
1B
b0 (
0A
b10100 !
b10100 '
0K
01
0:
1C
0<
0L
1E
0G
0-
06
0?
1H
b10100 $
b1000 #
b1000 &
#2010
b10101 !
b10101 '
10
11
1-
b10101 $
b1001 #
b1001 &
#2020
00
b10110 !
b10110 '
19
01
1:
0-
16
b10110 $
b1010 #
b1010 &
#2030
b10111 !
b10111 '
10
11
1-
b10111 $
b1011 #
b1011 &
#2040
1K
1G
1F
1I
00
09
b11000 !
b11000 '
0B
b100 (
1A
01
0:
0C
1<
0-
06
1?
b11000 $
b1100 #
b1100 &
#2050
b11001 !
b11001 '
10
11
1-
b11001 $
b1101 #
b1101 &
#2060
00
b11010 !
b11010 '
19
01
1:
0-
16
b11010 $
b1110 #
b1110 &
#2070
b11011 !
b11011 '
10
11
1-
b11011 $
b1111 #
b1111 &
